rg15/__init__.py
rg15/sensor.py
rg15-0.6.1.dist-info/LICENSE
rg15-0.6.1.dist-info/WHEEL
rg15-0.6.1.dist-info/METADATA
rg15-0.6.1.dist-info/RECORD
