Metadata-Version: 2.1
Name: rg15
Version: 0.6.1
Summary: rg15 library
Author-email: Elyas Bianchi <elyasb99@gmail.com>
Classifier: License :: OSI Approved :: MIT License
Project-URL: Home, https://github.com/Elyasb14/rg15
